<?xml version="1.0" encoding="UTF-8"?>
<list xmlns:xsi="http://www.w3.org/2001/XMLSchema-instance" xsi:noNamespaceSchemaLocation="../xsd/multisell.xsd">
	<npcs>
		<npc>65001</npc> <!-- Cornelius (Trader) -->
	</npcs>
	<item>
		<!--Blue Eva -->
		<ingredient count="10000000" id="57" />
		<!-- Forgotten Scroll : Anti-Magic Armor  -->
		<production count="1" id="10554" />
	</item>
	<item>
		<!--Blue Eva -->
		<ingredient count="10000000" id="57" />
		<!-- Forgotten Scroll : Archer's Will -->
		<production count="1" id="10553" />
	</item>
	<item>
		<!--Blue Eva -->
		<ingredient count="10000000" id="57" />
		<!-- Forgotten Scroll : Arrow Rain  -->
		<production count="1" id="14179" />
	</item>
	<item>
		<!--Blue Eva -->
		<ingredient count="10000000" id="57" />
		<!-- Forgotten Scroll : Blessing of Eva  -->
		<production count="1" id="10586" />
	</item>
	<item>
		<!--Blue Eva -->
		<ingredient count="10000000" id="57" />
		<!-- Forgotten Scroll : Deflect Magic  -->
		<production count="1" id="14207" />
	</item>
	<item>
		<!--Blue Eva -->
		<ingredient count="10000000" id="57" />
		<!-- Forgotten Scroll : Demolition Impact  -->
		<production count="1" id="10570" />
	</item>
	<item>
		<!--Blue Eva -->
		<ingredient count="10000000" id="57" />
		<!-- Forgotten Scroll : Dread Pool  -->
		<production count="1" id="10567" />
	</item>
	<item>
		<!--Blue Eva -->
		<ingredient count="10000000" id="57" />
		<!-- Forgotten Scroll : Dual Dagger Mastery  -->
		<production count="1" id="14210" />
	</item>
	<item>
		<!--Blue Eva -->
		<ingredient count="10000000" id="57" />
		<!-- Forgotten Scroll : Enlightenment Healer  -->
		<production count="1" id="14213" />
	</item>
	<item>
		<!--Blue Eva -->
		<ingredient count="10000000" id="57" />
		<!-- Forgotten Scroll : Enlightenment Wizard  -->
		<production count="1" id="14212" />
	</item>
	<item>
		<!--Blue Eva -->
		<ingredient count="10000000" id="57" />
		<!-- Forgotten Scroll : Eva's Will/Touch of Eva  -->
		<production count="1" id="14173" />
	</item>
	<item>
		<!--Blue Eva -->
		<ingredient count="10000000" id="57" />
		<!-- Forgotten Scroll : Excessive Loyalty  -->
		<production count="1" id="10577" />
	</item>
	<item>
		<!--Blue Eva -->
		<ingredient count="10000000" id="57" />
		<!-- Forgotten Scroll : Exciting Adventure  -->
		<production count="1" id="10561" />
	</item>
	<item>
		<!--Blue Eva -->
		<ingredient count="10000000" id="57" />
		<!-- Forgotten Scroll : Expose Weak Point  -->
		<production count="1" id="10560" />
	</item>
	<item>
		<!--Blue Eva -->
		<ingredient count="10000000" id="57" />
		<!-- Forgotten Scroll : Fighter's Will  -->
		<production count="1" id="10552" />
	</item>
	<item>
		<!--Blue Eva -->
		<ingredient count="10000000" id="57" />
		<!-- Forgotten Scroll : Final Secret  -->
		<production count="1" id="14208" />
	</item>
	<item>
		<!--Blue Eva -->
		<ingredient count="10000000" id="57" />
		<!-- Forgotten Scroll : Flame Armor  -->
		<production count="1" id="10572" />
	</item>
	<item>
		<!--Blue Eva -->
		<ingredient count="10000000" id="57" />
		<!-- Forgotten Scroll : Flame Hawk  -->
		<production count="1" id="10564" />
	</item>
	<item>
		<!--Blue Eva -->
		<ingredient count="10000000" id="57" />
		<!-- Forgotten Scroll : Force of Destruction  -->
		<production count="1" id="14182" />
	</item>
	<item>
		<!--Blue Eva -->
		<ingredient count="10000000" id="57" />
		<!-- Forgotten Scroll : Frost Armor  -->
		<production count="1" id="10573" />
	</item>
	<item>
		<!--Blue Eva -->
		<ingredient count="10000000" id="57" />
		<!-- Forgotten Scroll : Ghost Piercing  -->
		<production count="1" id="10566" />
	</item>
	<item>
		<!--Blue Eva -->
		<ingredient count="10000000" id="57" />
		<!-- Forgotten Scroll : Ghost Walking  -->
		<production count="1" id="10563" />
	</item>
	<item>
		<!--Blue Eva -->
		<ingredient count="10000000" id="57" />
		<!-- Forgotten Scroll : Golem Armor  -->
		<production count="1" id="10571" />
	</item>
	<item>
		<!--Blue Eva -->
		<ingredient count="10000000" id="57" />
		<!-- Forgotten Scroll : Hell Scream  -->
		<production count="1" id="14171" />
	</item>
	<item>
		<!--Blue Eva -->
		<ingredient count="10000000" id="57" />
		<!-- Forgotten Scroll : Hide  -->
		<production count="1" id="14209" />
	</item>
	<item>
		<!--Blue Eva -->
		<ingredient count="10000000" id="57" />
		<!-- Forgotten Scroll : Hurricane Armor  -->
		<production count="1" id="10574" />
	</item>
	<item>
		<!--Blue Eva -->
		<ingredient count="10000000" id="57" />
		<!-- Forgotten Scroll : Lightning Shock  -->
		<production count="1" id="10595" />
	</item>
	<item>
		<!--Blue Eva -->
		<ingredient count="10000000" id="57" />
		<!-- Forgotten Scroll : Lord of Vampire  -->
		<production count="1" id="10587" />
	</item>
	<item>
		<!--Blue Eva -->
		<ingredient count="10000000" id="57" />
		<!-- Forgotten Scroll : Magician's Will  -->
		<production count="1" id="14219" />
	</item>
	<item>
		<!--Blue Eva -->
		<ingredient count="10000000" id="57" />
		<!-- Forgotten Scroll : Meteor  -->
		<production count="1" id="14191" />
	</item>
	<item>
		<!--Blue Eva -->
		<ingredient count="10000000" id="57" />
		<!-- Forgotten Scroll : Mutual Response  -->
		<production count="1" id="10578" />
	</item>
	<item>
		<!--Blue Eva -->
		<ingredient count="10000000" id="57" />
		<!-- Forgotten Scroll : Pain of Shilen/Spirit of Shilen -->
		<production count="1" id="10593" />
	</item>
	<item>
		<!--Blue Eva -->
		<ingredient count="10000000" id="57" />
		<!-- Forgotten Scroll : Seal of Limit  -->
		<production count="1" id="10589" />
	</item>
	<item>
		<!--Blue Eva -->
		<ingredient count="10000000" id="57" />
		<!-- Forgotten Scroll : Seed of Revenge  -->
		<production count="1" id="10555" />
	</item>
	<item>
		<!--Blue Eva -->
		<ingredient count="10000000" id="57" />
		<!-- Forgotten Scroll : Servitor Barrier  -->
		<production count="1" id="10576" />
	</item>
	<item>
		<!--Blue Eva -->
		<ingredient count="10000000" id="57" />
		<!-- Forgotten Scroll : Seven Arrow  -->
		<production count="1" id="14211" />
	</item>
	<item>
		<!--Blue Eva -->
		<ingredient count="10000000" id="57" />
		<!-- Forgotten Scroll : Silent Mind  -->
		<production count="1" id="14220" />
	</item>
	<item>
		<!--Blue Eva -->
		<ingredient count="10000000" id="57" />
		<!-- Forgotten Scroll : Sixth Sense -->
		<production count="1" id="10559" />
	</item>
	<item>
		<!--Blue Eva -->
		<ingredient count="10000000" id="57" />
		<!-- Forgotten Scroll : Spirit of Phoenix/Flame Icon  -->
		<production count="1" id="10591" />
	</item>
	<item>
		<!--Blue Eva -->
		<ingredient count="10000000" id="57" />
		<!-- Forgotten Scroll : Star Fall  -->
		<production count="1" id="14192" />
	</item>
	<item>
		<!--Blue Eva -->
		<ingredient count="10000000" id="57" />
		<!-- Forgotten Scroll : Sublime Self Sacrifice  -->
		<production count="1" id="10585" />
	</item>
	<item>
		<!--Blue Eva -->
		<ingredient count="10000000" id="57" />
		<!-- Forgotten Scroll : Turn Stone  -->
		<production count="1" id="14221" />
	</item>
	<item>
		<!--Blue Eva -->
		<ingredient count="10000000" id="57" />
		<!-- Forgotten Scroll : Vampiric Mist  -->
		<production count="1" id="10575" />
	</item>
	<item>
		<!--Blue Eva -->
		<ingredient count="10000000" id="57" />
		<!-- Forgotten Scroll : Wild Shot  -->
		<production count="1" id="10594" />
	</item>
	<item>
		<!--Blue Eva -->
		<ingredient count="10000000" id="57" />
		<!-- Forgotten Scroll : Wind Riding  -->
		<production count="1" id="14176" />
	</item>
	<item>
		<!--Blue Eva -->
		<ingredient count="15000000" id="57" />
		<!-- Forgotten Scroll : Create Item Lv 10  -->
		<production count="1" id="17030" />
	</item>
	<item>
		<!--Blue Eva -->
		<ingredient count="15000000" id="57" />
		<!-- Forgotten Scroll : Protection of Alignement  -->
		<production count="1" id="10551" />
	</item>
	<item>
		<!--Blue Eva -->
		<ingredient count="15000000" id="57" />
		<!-- Forgotten Scroll : Protection of Elemental  -->
		<production count="1" id="10550" />
	</item>
	<item>
		<!--Blue Eva -->
		<ingredient count="15000000" id="57" />
		<!-- Forgotten Scroll : Protection of Rune  -->
		<production count="1" id="10549" />
	</item>
	<item>
		<!--Blue Eva -->
		<ingredient count="20000000" id="57" />
		<!-- Forgotten Scroll : Counter Critical  -->
		<production count="1" id="14225" />
	</item>
	<item>
		<!--Blue Eva -->
		<ingredient count="20000000" id="57" />
		<!-- Forgotten Scroll : Dance of Berserker  -->
		<production count="1" id="14199" />
	</item>
	<item>
		<!--Blue Eva -->
		<ingredient count="20000000" id="57" />
		<!-- Forgotten Scroll : Dual Blow  -->
		<production count="1" id="14218" />
	</item>
	<item>
		<!--Blue Eva -->
		<ingredient count="20000000" id="57" />
		<!-- Forgotten Scroll : Eye for Eye  -->
		<production count="1" id="14223" />
	</item>
	<item>
		<!--Blue Eva -->
		<ingredient count="20000000" id="57" />
		<!-- Forgotten Scroll : Great Fury  -->
		<production count="1" id="14227" />
	</item>
	<item>
		<!--Blue Eva -->
		<ingredient count="20000000" id="57" />
		<!-- Forgotten Scroll : Lucky Strike  -->
		<production count="1" id="14222" />
	</item>
	<item>
		<!--Blue Eva -->
		<ingredient count="20000000" id="57" />
		<!-- Forgotten Scroll : Maximum Force Focus  -->
		<production count="1" id="14201" />
	</item>
	<item>
		<!--Blue Eva -->
		<ingredient count="20000000" id="57" />
		<!-- Forgotten Scroll : Maximum Sonic Focus  -->
		<production count="1" id="14202" />
	</item>
	<item>
		<!--Blue Eva -->
		<ingredient count="20000000" id="57" />
		<!-- Forgotten Scroll : Onslaught of Pa'agrio  -->
		<production count="1" id="14226" />
	</item>
	<item>
		<!--Blue Eva -->
		<ingredient count="20000000" id="57" />
		<!-- Forgotten Scroll : Song of Purification  -->
		<production count="1" id="14198" />
	</item>
	<item>
		<!--Blue Eva -->
		<ingredient count="20000000" id="57" />
		<!-- Forgotten Scroll : Spirit of the Cat  -->
		<production count="1" id="14204" />
	</item>
	<item>
		<!--Blue Eva -->
		<ingredient count="20000000" id="57" />
		<!-- Forgotten Scroll : Spirit of the Phantom  -->
		<production count="1" id="14206" />
	</item>
	<item>
		<!--Blue Eva -->
		<ingredient count="20000000" id="57" />
		<!-- Forgotten Scroll : Spirit of the Unicorn  -->
		<production count="1" id="14205" />
	</item>
	<item>
		<!--Blue Eva -->
		<ingredient count="20000000" id="57" />
		<!-- Forgotten Scroll : Summon Imperial Phoenix  -->
		<production count="1" id="14200" />
	</item>
</list>

