<?xml version="1.0" encoding="UTF-8"?>
<list xmlns:xsi="http://www.w3.org/2001/XMLSchema-instance" xsi:noNamespaceSchemaLocation="../../xsd/buylist.xsd">
	<npcs>
		<!-- Gludin -->
		<npc>30207</npc> <!-- Arodin -->
		<!-- Gludio -->
		<npc>30321</npc> <!-- Sydnia -->
		<!-- Althena -->
		<npc>30001</npc> <!-- Lector -->
		<!-- Shel'Oloth -->
		<npc>30135</npc> <!-- Iria -->	
		<!-- Dion -->
		<npc>30060</npc> <!-- Sabrin -->		
		<!-- Hindemith -->
		<npc>30516</npc> <!-- Reep -->	
		<!-- Naargdum -->
		<npc>30558</npc> <!-- Jakal -->
		<!-- Cefedellen -->
		<npc>30147</npc> <!-- Unoren -->	
		<!-- Gevurah -->
		<npc>32164</npc> <!-- Erinu -->
		<!-- Hunter village -->
		<npc>30684</npc> <!-- Viktor -->
		<!-- Giran -->
		<npc>30084</npc> <!-- Graham -->
		<!-- Aden -->
		<npc>30837</npc> <!-- Woodrow -->
		<!-- Goddard -->
		<npc>31256</npc> <!-- Leon -->
		<npc>31257</npc> <!-- Veronica -->
		<!-- Rune -->
		<npc>31300</npc> <!-- Drumond -->
		<npc>31301</npc> <!-- Nils -->
		<!-- Oren -->
		<npc>30179</npc> <!-- Raudia -->
		<!-- Schuttgart -->
		<npc>31945</npc> <!-- Auzendorff -->
		<npc>31946</npc> <!-- Hombre -->
		<!-- Heine -->
		<npc>30891</npc> <!-- Verona -->
	</npcs> 	
	<!-- No grade Weapon Fighter -->
	<item id="1" /> <!-- Short Sword -->
	<item id="4" /> <!-- Club -->
	<item id="11" /> <!-- Bone Dagger -->
	<item id="13" /> <!-- Short Bow -->
	<item id="3" /> <!-- Broadsword -->
	<item id="152" /> <!-- Heavy Chisel -->
	<item id="12" /> <!-- Knife -->
	<item id="215" /> <!-- Doom Dagger -->
	<item id="14" /> <!-- Bow -->
	<item id="5" /> <!-- Mace -->
	<item id="153" /> <!-- Sigil -->
	<item id="1333" /> <!-- Brandish -->
	<item id="66" /> <!-- Gladius -->
	<item id="67" /> <!-- Orcish Sword -->
	<item id="122" /> <!-- Handmade Sword -->
	<item id="154" /> <!-- Dwarven Mace -->
	<item id="216" /> <!-- Dirk -->
	<item id="271" /> <!-- Hunting Bow -->
	<item id="2" /> <!-- Long Sword -->
	<item id="218" /> <!-- Throwing Knife -->
	<item id="272" /> <!-- Forest Bow -->
	<item id="15" /> <!-- Short Spear -->
	<item id="5284" /> <!-- Zweihander -->
	<!-- D grade Weapon Fighter -->
	<item id="2499" /> <!-- Elven Long Sword -->
	<item id="130" /> <!-- Elven Sword -->
	<item id="69" /> <!-- Bastard Sword -->
	<item id="70" /> <!-- Claymore -->
	<item id="158" /> <!-- Tarbar -->
	<item id="168" /> <!-- Work Hammer -->
	<item id="225" /> <!-- Mithril Dagger -->
	<item id="276" /> <!-- Elven Bow -->
	<item id="280" /> <!-- Light Crossbow -->
	<item id="258" /> <!-- Bagh-Nakh -->
	<item id="296" /> <!-- Dwarven Pike -->
	<item id="93" /> <!-- Winged Spear -->
</list>